{
  "creds": {
    "noiseKey": {
      "private": {
        "type": "Buffer",
        "data": "6MuYUivzS+t2NPiKu/aQdGFI+nMuPwJdj2n1Zfldol4="
      },
      "public": {
        "type": "Buffer",
        "data": "jINRCSmRg9uwu+NK7cr+wBhcgegJrf9Q3AuDI45sHWQ="
      }
    },
    "signedIdentityKey": {
      "private": {
        "type": "Buffer",
        "data": "MNAgsEDurWAV/fphV4SLbXMhdjYdsuQXmIGDxYWcJ2o="
      },
      "public": {
        "type": "Buffer",
        "data": "XnqSyLCx4Vr1zBA45LDZpASra8NAaCAVdov2ScfYeA4="
      }
    },
    "signedPreKey": {
      "keyPair": {
        "private": {
          "type": "Buffer",
          "data": "qP7RhSXE/X+uPKiyEjgkf2oj+934BwbFy9WrS5H2s0E="
        },
        "public": {
          "type": "Buffer",
          "data": "aeLmSUWp4YzHY6ShH7LJ+niXxcjoJUp+mBZbPrQpBRo="
        }
      },
      "signature": {
        "type": "Buffer",
        "data": "dQ8+KR2qru4UsjkkGhI0hdxxxNRITlZmV98VXNRx5wZvjt0JigtSr0qKDeOtqMB5ag/Xf74I/WiTpPIoFRCCjQ=="
      },
      "keyId": 1
    },
    "registrationId": 232,
    "advSecretKey": "FxryZ0udheTIuZ4fEs0Bebx/n+DLHI1NFKnmj/x5fY4=",
    "processedHistoryMessages": [
      {
        "key": {
          "remoteJid": "6281325610495@s.whatsapp.net",
          "fromMe": true,
          "id": "C430673B7885C4CCF67F83F2050FCB7E"
        },
        "messageTimestamp": 1664366063
      },
      {
        "key": {
          "remoteJid": "6281325610495@s.whatsapp.net",
          "fromMe": true,
          "id": "A70F6BDF70BC83AAAC9B780EA2847551"
        },
        "messageTimestamp": 1664366064
      },
      {
        "key": {
          "remoteJid": "6281325610495@s.whatsapp.net",
          "fromMe": true,
          "id": "380A863B9F69DDA96F04574F0C1419AA"
        },
        "messageTimestamp": 1664366066
      }
    ],
    "nextPreKeyId": 34,
    "firstUnuploadedPreKeyId": 34,
    "accountSettings": {
      "unarchiveChats": false
    },
    "account": {
      "details": "CKHMtacCEOrr0JkGGAE=",
      "accountSignatureKey": "IN9ES74LZMFIj7G7KrsOGCxZJJROC5QI+jQYnETgkhw=",
      "accountSignature": "tbeGyQiNiucgsqounwZ1vyI42usPI1KOnelAWXEzhRUu1W6i+ZuE2UMsDMEtcpfNfCknRwTm49/to9JJ95cnCQ==",
      "deviceSignature": "rBFuEC4JiG8b/liirRGUwq0MBon0Oww0rbDuksvlp4VZ8hKGsBrEZKACvEXNLcUBJadb3JnYPplg/VY2Q5Chig=="
    },
    "me": {
      "id": "6281325610495:9@s.whatsapp.net",
      "name": "FBOT",
      "jid": "6281325610495@s.whatsapp.net"
    },
    "signalIdentities": [
      {
        "identifier": {
          "name": "6281325610495:9@s.whatsapp.net",
          "deviceId": 0
        },
        "identifierKey": {
          "type": "Buffer",
          "data": "BSDfREu+C2TBSI+xuyq7DhgsWSSUTguUCPo0GJxE4JIc"
        }
      }
    ],
    "platform": "android",
    "lastAccountSyncTimestamp": 1664366062,
    "myAppStateKeyId": "AAAAABsr"
  },
  "keys": {
    "preKeys": {
      "1": null,
      "2": {
        "private": {
          "type": "Buffer",
          "data": "yHIGvTtoRpO+NBdQhMM+nlsweliYOZm6eKpGhxPmkkc="
        },
        "public": {
          "type": "Buffer",
          "data": "WtP1fgP9gwUepq0ryBNaa7lGzjJYhbZV/7ruYQWC/Qo="
        }
      },
      "3": {
        "private": {
          "type": "Buffer",
          "data": "6D6GiaQdAJwpFEwtaMlrJuCO/jdGP363AQy+uTbzZG8="
        },
        "public": {
          "type": "Buffer",
          "data": "DmasaPDuAf88ss4PakUr+BHGGvfzcLz+GhFBWD/Mr3Q="
        }
      },
      "4": {
        "private": {
          "type": "Buffer",
          "data": "6NWBP2+xhx1GhWbWQHuHHxVtkr8NKyZ19czr48lH/HA="
        },
        "public": {
          "type": "Buffer",
          "data": "f1R2C1BkSL3xpf0oIy0MEMBPh7Uymam9e6/2iP3jAjs="
        }
      },
      "5": {
        "private": {
          "type": "Buffer",
          "data": "yCYpZm8ut/07UcVThD4GVrs2v7rS/GH2lgsER0bQ3n4="
        },
        "public": {
          "type": "Buffer",
          "data": "RaqjUaOM0GOvsfOk6dpRz32RC4n12aj8c6EdQz7ssEI="
        }
      },
      "6": {
        "private": {
          "type": "Buffer",
          "data": "KI+YC6Y8MfzLvlARjyHE0oHtrDbMIeNgiFOcKnvSLUw="
        },
        "public": {
          "type": "Buffer",
          "data": "xhiZZXiP+RJzGh6+eRkvAGq9puVSA6ypNYWPnBikw0E="
        }
      },
      "7": null,
      "8": {
        "private": {
          "type": "Buffer",
          "data": "GLzi3ihmpB4NQLDw9XudOrvjvT7Tf/dYvlUQynFJw3Y="
        },
        "public": {
          "type": "Buffer",
          "data": "AgVR940DK3+0DyiGIDkb0ontegGhvdvjCqOZ1xULXXM="
        }
      },
      "9": {
        "private": {
          "type": "Buffer",
          "data": "GBJHQ40T+IpnUh8H/Vt7cv/GrRZ4223U7QHLN1Ia31E="
        },
        "public": {
          "type": "Buffer",
          "data": "M0c/fiahoO/SyBxIllO66aBJNHSfexI8sPXWGarbf0Q="
        }
      },
      "10": {
        "private": {
          "type": "Buffer",
          "data": "cMFCjFXp7F9iqdKGf4MkZ6WDRidx/8oBjlHFueD6eFU="
        },
        "public": {
          "type": "Buffer",
          "data": "p7u4hdO1AuRJkqZVTHALcc15cEmUq7+jRQJ3JF2nVUk="
        }
      },
      "11": null,
      "12": {
        "private": {
          "type": "Buffer",
          "data": "mJ5zdICt0Fp3gOEb9PmpddngZZSQRqfgL2EBO/JegFc="
        },
        "public": {
          "type": "Buffer",
          "data": "X3H5WY+iKwgszFWjvHcKc8qCUgkvCTNwtw47pwTpkUk="
        }
      },
      "13": {
        "private": {
          "type": "Buffer",
          "data": "8N53knUcL9dSDI8yYkKFQCxH0mfpsWhbkLxQ0rjsEk4="
        },
        "public": {
          "type": "Buffer",
          "data": "YFwvyx0lkGGNVNSBPkIVcukqEJgavYeuCA84yg1I7gA="
        }
      },
      "14": {
        "private": {
          "type": "Buffer",
          "data": "iBkH1dZrhOAMk10FnI5Y2QynJtHFIy8MHqxPR8hEtXI="
        },
        "public": {
          "type": "Buffer",
          "data": "jhcrBzFehf4mINL2tEftWTtr+JwCiYXS5hMVQJL18EI="
        }
      },
      "15": {
        "private": {
          "type": "Buffer",
          "data": "+AGP0WpTXQjhW7ba2QJezDjg/ChxUWGoT0QWgL7E7V4="
        },
        "public": {
          "type": "Buffer",
          "data": "FYjkZDo4xtX2Bm9Gf+ZjcmP/rvT24njoTYWJrLj+i2g="
        }
      },
      "16": {
        "private": {
          "type": "Buffer",
          "data": "UAllVlTTmJQjoDaSShkFCJp3gvbY0s1UzZkCSKMONmA="
        },
        "public": {
          "type": "Buffer",
          "data": "dG0f1IU9tD6DakN/1PkCkAAbGsa10Dox1TkauDmQ3jY="
        }
      },
      "17": null,
      "18": {
        "private": {
          "type": "Buffer",
          "data": "0POySdfTZrvd4K6akLBUMuDwGYw55TUAII/UXvwxQm0="
        },
        "public": {
          "type": "Buffer",
          "data": "iDfLhmYSrl0AdNeOFaB/b/Z8o9442z2tM8HRpM7SZQw="
        }
      },
      "19": {
        "private": {
          "type": "Buffer",
          "data": "yLI2zNmIjXRqXEMhdBvduJST5qln0ZWeu1vTFcnKL2s="
        },
        "public": {
          "type": "Buffer",
          "data": "nzvUoZtzbs3v39jyM7bPjrA+Nus3UYRJWHjvHlUAzAg="
        }
      },
      "20": {
        "private": {
          "type": "Buffer",
          "data": "YPCIIGK3CzzFaZV9ms6R0Yl5AlMAgKytQVlxwo3IQUQ="
        },
        "public": {
          "type": "Buffer",
          "data": "8SKfgA3Qj0hZGfYLqTqJWiY4bY4CnTNYisZuTAZX91k="
        }
      },
      "21": {
        "private": {
          "type": "Buffer",
          "data": "OFj4vzZcKcSX0aqHnkijCLVvCmg2Rp4JNlzrOHg3XEQ="
        },
        "public": {
          "type": "Buffer",
          "data": "wgPePtjWqMLdOKT/8K3FKkTIrU6DKP9JBnsfg3HqNy4="
        }
      },
      "22": {
        "private": {
          "type": "Buffer",
          "data": "+Nlv8lb0SO9kRta746aeR0mHI4QHGic13+TwpBF7c2c="
        },
        "public": {
          "type": "Buffer",
          "data": "kqvGIWRvctz+A1dlISKh6E+y3aOGHo5NH4/71i82PnM="
        }
      },
      "23": {
        "private": {
          "type": "Buffer",
          "data": "OAcfMnnCQ+HkMc9XbWaxTQ99fTpssW7ng6TwmtiKgmQ="
        },
        "public": {
          "type": "Buffer",
          "data": "Zn/da3KGUWEFDdLlNA3ES7m3USvhr63y++ShcgCZoh0="
        }
      },
      "24": {
        "private": {
          "type": "Buffer",
          "data": "4EKuqAqvsWJnwhcw5qd573a6+1fdshWS0LHgQLvw8H0="
        },
        "public": {
          "type": "Buffer",
          "data": "D3J9X9qbUfUqLPtxBQh9bUQ5O5EVE1mzkldok3frhkI="
        }
      },
      "25": {
        "private": {
          "type": "Buffer",
          "data": "yJcEcouFM648ErYhM1Hgeo433tlOoMkslthDNT37RmE="
        },
        "public": {
          "type": "Buffer",
          "data": "z/zGitnGHW83OpnFQVkSSfO9Tw5fL/9vyTmnAC01GSU="
        }
      },
      "26": {
        "private": {
          "type": "Buffer",
          "data": "mFcgMmqKPPfA0cCSCTdLgc5Do91U10BYda7JaK6QHns="
        },
        "public": {
          "type": "Buffer",
          "data": "miQVMvOmipkjHneHrrkhvUtJK2VG1hr1/M+gUb/slFo="
        }
      },
      "27": {
        "private": {
          "type": "Buffer",
          "data": "KDQYMN1JvMVcaFFg/siVp1F+rRkkhyH+a8tn0AVxGHA="
        },
        "public": {
          "type": "Buffer",
          "data": "NSRTMTgN9iwuY/JykqF9iuTFe0wpd6QX8csKp45GVFY="
        }
      },
      "28": {
        "private": {
          "type": "Buffer",
          "data": "EEMqe+kvwhBdXEHlUykdfGNi1uy0v5jGJ96CTzXFCWc="
        },
        "public": {
          "type": "Buffer",
          "data": "RlIN2Xi8pe/7djc3eymu6agCGWWCCgmzPBYC7RIkJTY="
        }
      },
      "29": null,
      "30": {
        "private": {
          "type": "Buffer",
          "data": "AJT0F//FvQEX07rvQxDITieuP58IbHjq9KlV5u0YLGY="
        },
        "public": {
          "type": "Buffer",
          "data": "zHpUi8AtlZ8waWc9A1fOPkM/NwUZuyHGiLANMJ55SUc="
        }
      },
      "31": null,
      "32": null,
      "33": {
        "private": {
          "type": "Buffer",
          "data": "CC7V9MkoLMuKExnZWqWBxSArJxJmJXtOCCtg6fUuYHg="
        },
        "public": {
          "type": "Buffer",
          "data": "n0lFGtGsXVEO725TRucOU7dBcFhUquJ6Dry5sMnQ2Tw="
        }
      }
    },
    "sessions": {
      "6281325610495.0": {
        "_sessions": {
          "BWsHfFATfHaj6kpgu/JTNTkaRFj7HLcp7vNSEocgw3cG": {
            "registrationId": 597065817,
            "currentRatchet": {
              "ephemeralKeyPair": {
                "pubKey": "BbJRRXRSEZk63zJWbyTpCIG002ZNjrGCJXX8vAM/OgAN",
                "privKey": "MB5juUkvwOYKDgONqzgqALRxL2nUF6rzyee7Ko073Gs="
              },
              "lastRemoteEphemeralKey": "BZhinVf7V8SCQ1DbtX8zg8Z/yiNbcpGLYNhO6jTsWLVA",
              "previousCounter": 1,
              "rootKey": "kQaSd/mMRsy2g4e55h2DcMBeWR844KM2kU+tHuD6I18="
            },
            "indexInfo": {
              "baseKey": "BWsHfFATfHaj6kpgu/JTNTkaRFj7HLcp7vNSEocgw3cG",
              "baseKeyType": 2,
              "closed": -1,
              "used": 1664366122126,
              "created": 1664366061890,
              "remoteIdentityKey": "BSDfREu+C2TBSI+xuyq7DhgsWSSUTguUCPo0GJxE4JIc"
            },
            "_chains": {
              "BR8t94+icd07ypG9aPc07AB0KRKmmvuna59buos1E5Fl": {
                "chainKey": {
                  "counter": 5
                },
                "chainType": 2,
                "messageKeys": {}
              },
              "BZt5DhVHA/f0dRXZkkk17x7r/gOWysUfvOHu2lggiPtr": {
                "chainKey": {
                  "counter": 2
                },
                "chainType": 2,
                "messageKeys": {}
              },
              "BZhinVf7V8SCQ1DbtX8zg8Z/yiNbcpGLYNhO6jTsWLVA": {
                "chainKey": {
                  "counter": 0,
                  "key": "0s6cF5m2BZ8OQIcnrZay33GIN9BVTTRi3JjP7MIml+0="
                },
                "chainType": 2,
                "messageKeys": {}
              },
              "BbJRRXRSEZk63zJWbyTpCIG002ZNjrGCJXX8vAM/OgAN": {
                "chainKey": {
                  "counter": 106,
                  "key": "4HNZ0d0nak56NnAAeC7Tt6+9iAjkg+mqT79QmYM4Jm4="
                },
                "chainType": 1,
                "messageKeys": {}
              }
            }
          }
        },
        "version": "v1"
      },
      "6285326794834.0": {
        "_sessions": {
          "BeEr9dslsVhTVzQvkCdcpm8G0RWdX4NKx1OKOqVUFc4c": {
            "registrationId": 1522547856,
            "currentRatchet": {
              "ephemeralKeyPair": {
                "pubKey": "BTG73N2+tDwWLFaHWALjrJITXmCrfTO1MTvgLKqXgLdQ",
                "privKey": "qOOkxBDIfdl8yLDmwSq3T3qENTIsjWpTXnqiNqJFkGs="
              },
              "lastRemoteEphemeralKey": "BRo0f2CeXXbNhP1nG1WMTFn17GfTrtzkqQrVGyGZonZp",
              "previousCounter": 0,
              "rootKey": "n/Ng39i+pKCYXSn+G2XT0LLdAtwvIx/PIz39y9OWrB4="
            },
            "indexInfo": {
              "baseKey": "BeEr9dslsVhTVzQvkCdcpm8G0RWdX4NKx1OKOqVUFc4c",
              "baseKeyType": 1,
              "closed": 1664636576017,
              "used": 1664366062486,
              "created": 1664366062486,
              "remoteIdentityKey": "BQJSy7PLU1NwNrA2Uz9lB0vwRWoLiax99bVLwkMCSUxl"
            },
            "_chains": {
              "BTG73N2+tDwWLFaHWALjrJITXmCrfTO1MTvgLKqXgLdQ": {
                "chainKey": {
                  "counter": 0,
                  "key": "E/nztEOxlFOEB/NqISzQcZkAem5PDhYe7SoEX1cqWQo="
                },
                "chainType": 1,
                "messageKeys": {}
              }
            },
            "pendingPreKey": {
              "signedKeyId": 2,
              "baseKey": "BeEr9dslsVhTVzQvkCdcpm8G0RWdX4NKx1OKOqVUFc4c",
              "preKeyId": 1890450
            }
          },
          "BdlV5UBUW1hugVkOSyQsElFSHCqo8GpE//jzr2dOii02": {
            "registrationId": 1522547856,
            "currentRatchet": {
              "ephemeralKeyPair": {
                "pubKey": "Ba00+o2SDTYJGiNyf16Gj/Z3OiOlq/17a9WAbvp0SNUd",
                "privKey": "OKlpSrv/dITp1f6N29Zv5ZtlCtkjJpBArn30SagfJm0="
              },
              "lastRemoteEphemeralKey": "BTuQMYy2yHgSHKFXOSYgynY0aRgDPVg6XlurZyk4PykN",
              "previousCounter": 1,
              "rootKey": "PSmNM5xx7jV1PDWOZUdd/M79jcvWRh2zUH2QyWVEDLA="
            },
            "indexInfo": {
              "baseKey": "BdlV5UBUW1hugVkOSyQsElFSHCqo8GpE//jzr2dOii02",
              "baseKeyType": 2,
              "closed": -1,
              "used": 1664642801765,
              "created": 1664636576025,
              "remoteIdentityKey": "BQJSy7PLU1NwNrA2Uz9lB0vwRWoLiax99bVLwkMCSUxl"
            },
            "_chains": {
              "BRzHjOpo+oifxPPIGtDBVgE9cMB3pkrdt7Z3Aq+TglYV": {
                "chainKey": {
                  "counter": 0
                },
                "chainType": 2,
                "messageKeys": {}
              },
              "BTnbYEqCDeiKiEoQNqBS7nezWH3MkQfuRN/Sa9YVqOhS": {
                "chainKey": {
                  "counter": 0
                },
                "chainType": 2,
                "messageKeys": {}
              },
              "BWxk2VHVJaZkn/ZjacFjRATWUmGlQVt86K6tTby/gLRQ": {
                "chainKey": {
                  "counter": 0
                },
                "chainType": 2,
                "messageKeys": {}
              },
              "BXEwwkVuUWo/77O+USKqciRPeMBG/4+y4ymQWNKl6WIa": {
                "chainKey": {
                  "counter": 1
                },
                "chainType": 2,
                "messageKeys": {}
              },
              "Baudu6Hp+Q6kf2O6UKsnK9yzsrjczsGNOjXpZwaM9PwX": {
                "chainKey": {
                  "counter": 0
                },
                "chainType": 2,
                "messageKeys": {}
              },
              "Bdk1SBjnGX44u0HNT3h7OIeFXHgDyQZQtFmcNqRF23JL": {
                "chainKey": {
                  "counter": 0
                },
                "chainType": 2,
                "messageKeys": {}
              },
              "BeXfuvNo3Rh6wwYNB/EdSptKyIx6PgWY6AfAPJlk75Q8": {
                "chainKey": {
                  "counter": 0
                },
                "chainType": 2,
                "messageKeys": {}
              },
              "BVIzWS3oUwKOVbd8nlDvcLfW6w+ICuaL4++r3+V8FiEZ": {
                "chainKey": {
                  "counter": 1
                },
                "chainType": 2,
                "messageKeys": {}
              },
              "BWPCxd4qg/zDMyaklWbshi/mmaNqq8t2NUit+qdNKJkE": {
                "chainKey": {
                  "counter": 1
                },
                "chainType": 2,
                "messageKeys": {}
              },
              "Beodf6JLt0tBKWcNzS/+EgiAsUqFLPMN0yTvRGfdafgO": {
                "chainKey": {
                  "counter": 0
                },
                "chainType": 2,
                "messageKeys": {}
              },
              "BXurizrUQai9YtvNV8lAh1Q9hYPxPhzX92xu5DkHc6Na": {
                "chainKey": {
                  "counter": 2
                },
                "chainType": 2,
                "messageKeys": {}
              },
              "BR/NRnT98kruc39Ivev9nEZBlXy+3imy07WAN+AYHtlP": {
                "chainKey": {
                  "counter": 0
                },
                "chainType": 2,
                "messageKeys": {}
              },
              "BWD4DJuYGE1hGXwgQkc3MvSOplYVkbPmv5McQ2VsEyMS": {
                "chainKey": {
                  "counter": 0
                },
                "chainType": 2,
                "messageKeys": {}
              },
              "BSJvLv+xYA189iLv40Qbm8/L/GqN6c2+SuOxsiRGsmc3": {
                "chainKey": {
                  "counter": 0
                },
                "chainType": 2,
                "messageKeys": {}
              },
              "Bay9LuQGQb2envLpORkmH894bZu5CAZZXjNTCTyvgFkV": {
                "chainKey": {
                  "counter": 0
                },
                "chainType": 2,
                "messageKeys": {}
              },
              "BS+oKrjbD6kkAGOWrOb4xhdv1OANpCDHxbuJwYikpiEh": {
                "chainKey": {
                  "counter": 0
                },
                "chainType": 2,
                "messageKeys": {}
              },
              "BVm+7GHFx47J8Y7tYvcZTb0PINqnJgofueFEXUikkd8R": {
                "chainKey": {
                  "counter": 0
                },
                "chainType": 2,
                "messageKeys": {}
              },
              "Bbg0iHW+W3/VEHDVufoB8n8zl9KyCxmtinVsZgj+veQa": {
                "chainKey": {
                  "counter": 1
                },
                "chainType": 2,
                "messageKeys": {}
              },
              "BQMNA2wElVxtRnhzGy5OjOCtwpYwPHyiD4HvTc+f0Ad+": {
                "chainKey": {
                  "counter": 2
                },
                "chainType": 2,
                "messageKeys": {}
              },
              "BYH5MpYqrLEYTRHxRZr3K3ZNBN7KNrRvH690GQWAkmQM": {
                "chainKey": {
                  "counter": 0
                },
                "chainType": 2,
                "messageKeys": {}
              },
              "BeQphsayagPOmnKgiYyLU3O27YzNpMxsbTwP9kWxwpB/": {
                "chainKey": {
                  "counter": 0
                },
                "chainType": 2,
                "messageKeys": {}
              },
              "BaeZX/rUGCksNgqVHcqRfY3uJYlTH0Ybxeoe9VqAGlw+": {
                "chainKey": {
                  "counter": 1
                },
                "chainType": 2,
                "messageKeys": {}
              },
              "BStjrAV16Nn5rqA+jgqLDzETX7PdHfAvV32Mgqkj2fMl": {
                "chainKey": {
                  "counter": 0
                },
                "chainType": 2,
                "messageKeys": {}
              },
              "BVHD9XmcAnDk8uNZZIl4oy4GFvO6J+iFgZWxkHIpl1sf": {
                "chainKey": {
                  "counter": 0
                },
                "chainType": 2,
                "messageKeys": {}
              },
              "BX6BvwA3lvPiprGeqIQGbraCs82gCWmYRGUy6+NiPSo1": {
                "chainKey": {
                  "counter": 0
                },
                "chainType": 2,
                "messageKeys": {}
              },
              "BfURgJ9SGMQW2hLS3mfYnpldF9ZZdi+hjdiseY7qtq5i": {
                "chainKey": {
                  "counter": 0
                },
                "chainType": 2,
                "messageKeys": {}
              },
              "BfdpDIK+LSf8bkfKz1R+941XARX/TmPNb4aDCXpVBM5E": {
                "chainKey": {
                  "counter": 0
                },
                "chainType": 2,
                "messageKeys": {}
              },
              "BXO+iLbJb6xRi0Qoho5vlfTXadMFn4N86I9j3EyBCNp1": {
                "chainKey": {
                  "counter": 0
                },
                "chainType": 2,
                "messageKeys": {}
              },
              "BQjNX2Xs1OEIzcPrSyW0pTty8UtTed1pYeal+pQzJW5B": {
                "chainKey": {
                  "counter": 0
                },
                "chainType": 2,
                "messageKeys": {}
              },
              "BZVJ0NSI22joN4NjsjWQA3hLtQyTUDgtDax8zsSkWFQo": {
                "chainKey": {
                  "counter": 0
                },
                "chainType": 2,
                "messageKeys": {}
              },
              "Be0OOtiAYkLGQIDiUYrsz67jW+LGcAJQxQd6gaS5OWBO": {
                "chainKey": {
                  "counter": 0
                },
                "chainType": 2,
                "messageKeys": {}
              },
              "Be1ghUQmCH+pShHTY4ZiJm+hqShR7O1DmteyIm02OiMM": {
                "chainKey": {
                  "counter": 0
                },
                "chainType": 2,
                "messageKeys": {}
              },
              "BcYpZtDvrvVKzW6CSM2SdvGzn4N/GaFVZYH1bePOpUR/": {
                "chainKey": {
                  "counter": 0
                },
                "chainType": 2,
                "messageKeys": {}
              },
              "Bd/Aug65hCEqXZ/x7Hj8IvrnRS/yENNm2i2IxRmdPn1F": {
                "chainKey": {
                  "counter": 0
                },
                "chainType": 2,
                "messageKeys": {}
              },
              "BfP5ZTwSirAwmTvEvqaqMhe/Mh6BXlLHvkwmfTD57kFZ": {
                "chainKey": {
                  "counter": 0
                },
                "chainType": 2,
                "messageKeys": {}
              },
              "BVj9gxiCMeQyhevOxECnpANW/q/nwjHXaF0t4esgK5wj": {
                "chainKey": {
                  "counter": 0
                },
                "chainType": 2,
                "messageKeys": {}
              },
              "BW2KBtDiZvfvptUjyIwDKOp6z0QTTKXQ1sWlSfVeamka": {
                "chainKey": {
                  "counter": 1
                },
                "chainType": 2,
                "messageKeys": {}
              },
              "Baqp8aKWMs0JW+ubdrFURQFRUzqqMqKqmNhkdxHY905v": {
                "chainKey": {
                  "counter": 0
                },
                "chainType": 2,
                "messageKeys": {}
              },
              "BV7CHTKjiJ21si0+uXTN7qJ47Utz9WAXipFyb1imNU9u": {
                "chainKey": {
                  "counter": 0
                },
                "chainType": 2,
                "messageKeys": {}
              },
              "BcbONQbD3TpxSw8PgagQ1Koo94BbPO37WIGBRjaOUY5L": {
                "chainKey": {
                  "counter": 0
                },
                "chainType": 2,
                "messageKeys": {}
              },
              "Bf9+Je+aCiljIof8vmu1qDEsFcIqEAU2zGwql+vSv7Q2": {
                "chainKey": {
                  "counter": 0
                },
                "chainType": 2,
                "messageKeys": {}
              },
              "BU/xyegacKXtbDZ7EY5RIJLRyhKTgAZ6UdMSVJfAhT1H": {
                "chainKey": {
                  "counter": 0
                },
                "chainType": 2,
                "messageKeys": {}
              },
              "BYFTNZg7oaCd5/YWpxl1OAUerHM6lSDzgz6QE8n/0Ow6": {
                "chainKey": {
                  "counter": 0
                },
                "chainType": 2,
                "messageKeys": {}
              },
              "BWE84BGy5YBIvCye03ja3zLIwD1ka2tdJKueOmnCxdhl": {
                "chainKey": {
                  "counter": 0
                },
                "chainType": 2,
                "messageKeys": {}
              },
              "BdDEE9d++Xtv0SkL5ckkv9OLMdYO0KmlAIXU88XlZJNO": {
                "chainKey": {
                  "counter": 0
                },
                "chainType": 2,
                "messageKeys": {}
              },
              "BWZRUccnF019iA7GdFR7aTHSF1ifRLIZqp4psCWcPkwm": {
                "chainKey": {
                  "counter": 1
                },
                "chainType": 2,
                "messageKeys": {}
              },
              "BfgKeCe5Z5Fgtf8cnYRlw8NE4BzsplHREpuvdqDh8apf": {
                "chainKey": {
                  "counter": 0
                },
                "chainType": 2,
                "messageKeys": {}
              },
              "BWzaGYTm+zTE6abYZKYVAZhAQhCOJA10Ki4gYLVG5aB2": {
                "chainKey": {
                  "counter": 1
                },
                "chainType": 2,
                "messageKeys": {}
              },
              "BSNAXvnt+DafvIA8GiQFHPRyR14dRV1pUbQ3k9OdCpwp": {
                "chainKey": {
                  "counter": 0
                },
                "chainType": 2,
                "messageKeys": {}
              },
              "BYww4IwIrS/zPEdfcCK8KWRJkJ4aQMz0U1kH+SKJkyc6": {
                "chainKey": {
                  "counter": 6
                },
                "chainType": 2,
                "messageKeys": {}
              },
              "BdxdWmpT1LUji3iqzWgOWpTOrDCkgQCzbYaMtRrgO1U1": {
                "chainKey": {
                  "counter": 0
                },
                "chainType": 2,
                "messageKeys": {}
              },
              "BewbalAoJTd16n3xBio9aVWF2Mg2r6X07lmScVCJvwhb": {
                "chainKey": {
                  "counter": 1
                },
                "chainType": 2,
                "messageKeys": {}
              },
              "BeitMhfycgsaoDMIZjP0sYV03tQrSbDFuvNICppaPO0E": {
                "chainKey": {
                  "counter": 0
                },
                "chainType": 2,
                "messageKeys": {}
              },
              "BQNRdCR2bZS69Azhk/8x+DT8JiWLARSb2ZvA4CeDhgld": {
                "chainKey": {
                  "counter": 0
                },
                "chainType": 2,
                "messageKeys": {}
              },
              "BYjqD8a4fU5c1AkJP4ZIujqNvgXaz/HMWxVNfZPG0fN6": {
                "chainKey": {
                  "counter": 0
                },
                "chainType": 2,
                "messageKeys": {}
              },
              "BZw0LRsFtGrokFNifaUyqPKUOQINkoidP/1E98TVH7Mm": {
                "chainKey": {
                  "counter": 0
                },
                "chainType": 2,
                "messageKeys": {}
              },
              "BXHfunZFJ9I8W/uXcPVBM1Rg2sb2M3q7GADwRDGvM/59": {
                "chainKey": {
                  "counter": 0
                },
                "chainType": 2,
                "messageKeys": {}
              },
              "BfFLqEYG+UQVyCxo9NiM5eiTIq6b5z7SxuT3mvusquYY": {
                "chainKey": {
                  "counter": 0
                },
                "chainType": 2,
                "messageKeys": {}
              },
              "BTuQMYy2yHgSHKFXOSYgynY0aRgDPVg6XlurZyk4PykN": {
                "chainKey": {
                  "counter": 0,
                  "key": "s5PDGt3N50NGWlfWIqI7zU18atJ/P9DolJPoLkSZxHM="
                },
                "chainType": 2,
                "messageKeys": {}
              },
              "Ba00+o2SDTYJGiNyf16Gj/Z3OiOlq/17a9WAbvp0SNUd": {
                "chainKey": {
                  "counter": 1,
                  "key": "Hn1Lk3KcM8CakUaTgPVxY44QzyS4d2Ew8X27WkAvmwo="
                },
                "chainType": 1,
                "messageKeys": {}
              }
            }
          }
        },
        "version": "v1"
      },
      "6288239447921.0": {
        "_sessions": {
          "BSPlG2aHnVfNVb8Zf4rfizMbyTwhv++SJs4m5s6iTn4f": {
            "registrationId": 2011433957,
            "currentRatchet": {
              "ephemeralKeyPair": {
                "pubKey": "BU88K9l5vNOnXcey54BXSJ8dVNA7lNyRBT3KC0HI2YZC",
                "privKey": "uOPMdrCvYnSzSftfpTcM2utM/GtjjRqwzhluElz2Sk8="
              },
              "lastRemoteEphemeralKey": "BVVDHOPPo6Q7pIykL3kZGfVr4xwPvKnP4NFDmOjTWr8U",
              "previousCounter": 0,
              "rootKey": "Q+pXY7N8OahcNLTkvWOmQFVXH1U2Lfo16fzKF5/bbB8="
            },
            "indexInfo": {
              "baseKey": "BSPlG2aHnVfNVb8Zf4rfizMbyTwhv++SJs4m5s6iTn4f",
              "baseKeyType": 1,
              "closed": -1,
              "used": 1664366135241,
              "created": 1664366082285,
              "remoteIdentityKey": "BZr44l2yzOzo6aXFWg0U9H/PmQ9S3nF7cvCYdJKgUKB2"
            },
            "_chains": {
              "BbNwy/AdhHr2f4MnxEgC6YLbaJRMJ17BVTr+2UpODm43": {
                "chainKey": {
                  "counter": 0
                },
                "chainType": 2,
                "messageKeys": {}
              },
              "BYNA40piZ7gqDknzGLQ4nTvaQVgeTPg0dp2QySq2uaNG": {
                "chainKey": {
                  "counter": 0
                },
                "chainType": 2,
                "messageKeys": {}
              },
              "BVVDHOPPo6Q7pIykL3kZGfVr4xwPvKnP4NFDmOjTWr8U": {
                "chainKey": {
                  "counter": 0,
                  "key": "t1913m4/joeyuec0Oer8lK6wTtE3h5l7IZtfRApSpjQ="
                },
                "chainType": 2,
                "messageKeys": {}
              },
              "BU88K9l5vNOnXcey54BXSJ8dVNA7lNyRBT3KC0HI2YZC": {
                "chainKey": {
                  "counter": -1,
                  "key": "8yrrXDzy/SKp9cup01LMBUrGnu/cYW6zaNSzCNpis1I="
                },
                "chainType": 1,
                "messageKeys": {}
              }
            }
          }
        },
        "version": "v1"
      },
      "6285225665895.0": {
        "_sessions": {
          "BSGvCIUZl0fGhLHX8/rfVq2xWACRqvRfPwAEYeTqTpZx": {
            "registrationId": 84689575,
            "currentRatchet": {
              "ephemeralKeyPair": {
                "pubKey": "Bb2sAAcUcx9LUG3rEwptDWQb6a4O0OSnSarpreVOJ50o",
                "privKey": "gLbZszb6r56YxkYRHiui0tYsmyGz/aLppSxRGwz522E="
              },
              "lastRemoteEphemeralKey": "BX38Ob3cu47/VxnpXt14mQeBrE8FryTwQjl16VVJ8FwH",
              "previousCounter": 0,
              "rootKey": "cfAMqzcVuwd3O/nohNqEbR5hpaR1XTTjdYFKXcWTcH0="
            },
            "indexInfo": {
              "baseKey": "BSGvCIUZl0fGhLHX8/rfVq2xWACRqvRfPwAEYeTqTpZx",
              "baseKeyType": 2,
              "closed": -1,
              "used": 1664636503951,
              "created": 1664636503951,
              "remoteIdentityKey": "BQCu0nYIVZZns1ygO8+0uadvG3DAulTCxG0JYfFgWCI5"
            },
            "_chains": {
              "BX38Ob3cu47/VxnpXt14mQeBrE8FryTwQjl16VVJ8FwH": {
                "chainKey": {
                  "counter": 20,
                  "key": "PsivGRXP+dk9wHOcNMhKtQ+yq9ACvLOnw6yRe8qwHkA="
                },
                "chainType": 2,
                "messageKeys": {
                  "0": "MoXmvF2z3pewxreCXMI+uVAEOdXIFP6i4cyHSCWl7W4=",
                  "1": "MTxj8+BBqpJyGJiN2WzUVeSizoHoeVrwXeGzF2bAlm4=",
                  "2": "WHGjvugjxao5W9usKLWlp8hFciIw+14BEZWJzSXlgto=",
                  "3": "46Cm4kzJo0E0IBc1dj2Buaeu7qKwbjlB8SpadWP+s/8=",
                  "4": "SsLvq6pU2iUYv8DIR2w3wgekwLRikj6bywjM0nvbc1M=",
                  "5": "W8K+j1+Hth6F5QlGPOIgkP9tYcGhcObq0x0AtGnHsxc=",
                  "6": "8xGFN5dj6Zm8KYK1ETA82pNqgvpeXI6kkQ/9uqA8Br4=",
                  "7": "RND0CWBu1rhP33WeWb40DNm3vNGrsJJUaI6g5BT3k5Q=",
                  "8": "uTpZfrCNi/NWV2PSPmzDRubOQgo9OvKLq7TtAGo5hos=",
                  "9": "u2vemzM7xzeiQWctwhcg8jhez22W8bk5i7l+u050fec=",
                  "10": "HBVDrmLUlimBsBptegyzCd3ilsq2HbWblt8PG5xo0pE=",
                  "11": "jsukn+P14lk56Ila+GlhcnbuXpaImJ9yYZbhgP6Vq7o=",
                  "12": "TaxvHCIjpeBhaLoO52JJg6P29aqKl/qFWEEI8TJxIBU=",
                  "13": "bBdV9O/K3HLCaexe0+o0/2AuTIxTox1X5QXKu64M/yU=",
                  "14": "XrAOTr1ST8ej03iFn/OQLcfnxLYzSXoHR1iraj/81M4=",
                  "15": "LNRbF6Jy3PEP1Xa7LMFtVPEMRKXlrTcqqOnyaEQ7s+Q=",
                  "16": "NJFhOhla3bKhYIMzwjZJBrVF2NIAKNhPi53l34LS/7w=",
                  "17": "tGdD/4uw7GgI2mbEmoAnvseNsZ8VUbmZRhMufczA37Q=",
                  "18": "XXWvYeX1QavbIc0VKMXoiqAczLhqCIk/ZKt+PMTVpzU="
                }
              },
              "Bb2sAAcUcx9LUG3rEwptDWQb6a4O0OSnSarpreVOJ50o": {
                "chainKey": {
                  "counter": -1,
                  "key": "ar7UYqa8Xd66gfmq9E275z7RJrqqi8maB4Zg03un8JU="
                },
                "chainType": 1,
                "messageKeys": {}
              }
            }
          }
        },
        "version": "v1"
      },
      "6285226643655.0": {
        "_sessions": {
          "BahSjH9vjYnKHmw1g+fU0CF9YghEObR+KPNDHF9xPewO": {
            "registrationId": 698341652,
            "currentRatchet": {
              "ephemeralKeyPair": {
                "pubKey": "BY9xNA17QaytvFtyfKNG8f64yiQlkwSSBrom/ynBU5MD",
                "privKey": "sFqYvn7AH7Og989tiIhGcQbKBeZ5ABoW38Z0aB2y4H8="
              },
              "lastRemoteEphemeralKey": "BbGY88yCaHgfW+CeXfQyQQlS28CUo/Q1YjbKK67LawJ9",
              "previousCounter": 0,
              "rootKey": "9jxiM/p13pVPSBUL66Dgnj1kligRM0BRrLcetRIGRAQ="
            },
            "indexInfo": {
              "baseKey": "BahSjH9vjYnKHmw1g+fU0CF9YghEObR+KPNDHF9xPewO",
              "baseKeyType": 2,
              "closed": -1,
              "used": 1664636503955,
              "created": 1664636503955,
              "remoteIdentityKey": "BQDH9HQv4kjoDj9so4KPkeMsfAjWgbu4V4FKKKJL6ksX"
            },
            "_chains": {
              "BbGY88yCaHgfW+CeXfQyQQlS28CUo/Q1YjbKK67LawJ9": {
                "chainKey": {
                  "counter": 4,
                  "key": "bEexr63Ua6zkqrMDD7nOrzZ4pqZISwXLopCC2+SV5D4="
                },
                "chainType": 2,
                "messageKeys": {
                  "0": "208xC/+ucaQeMxMnwyJBZr6OBEieH0raAITDRGSl2MM=",
                  "1": "sB0c20MOQjwbwvoFArRfh1pnz/GKs8+2wsK3uASDd/Y=",
                  "2": "JpgebuItefZviBvxn5Mda+T8S0W443CHv9wRymr+xwM=",
                  "3": "CzK4W49cRVq8MMiv0T1Lo0f2O/YgQcqwHpXjX/K9v1Y="
                }
              },
              "BY9xNA17QaytvFtyfKNG8f64yiQlkwSSBrom/ynBU5MD": {
                "chainKey": {
                  "counter": -1,
                  "key": "RavMl2u3IHAs+tJAAv/UCtaA09RO6vR7I2hj1NB8mzQ="
                },
                "chainType": 1,
                "messageKeys": {}
              }
            }
          }
        },
        "version": "v1"
      },
      "6281325004641.0": {
        "_sessions": {
          "Ba5gV3YTwfBpYe7MelQs5rVlrVLyTdGBLxeUxgBXH+Jc": {
            "registrationId": 1155989245,
            "currentRatchet": {
              "ephemeralKeyPair": {
                "pubKey": "BQOeIvGl1UWp2attWeeAW7YG/Qt2j5YN8ywY9WGeWGBp",
                "privKey": "2LmG9iYuKuE72ePriS1p7lZdVve6UNJcSldsOq5nkG4="
              },
              "lastRemoteEphemeralKey": "BS0RNqxB3RnZqxZlen5qBPj99h/SfHhUepaUyheUeK0N",
              "previousCounter": 0,
              "rootKey": "NUIHwTr4UcgYz8YZYuVKfv5LUMZMgu7KkF8fz71tvY0="
            },
            "indexInfo": {
              "baseKey": "Ba5gV3YTwfBpYe7MelQs5rVlrVLyTdGBLxeUxgBXH+Jc",
              "baseKeyType": 2,
              "closed": -1,
              "used": 1664636956188,
              "created": 1664636956188,
              "remoteIdentityKey": "BTSGzLHy0UzW+FVrE7fjdKK/LJVe7p3dTbgmPe9NBcAU"
            },
            "_chains": {
              "BS0RNqxB3RnZqxZlen5qBPj99h/SfHhUepaUyheUeK0N": {
                "chainKey": {
                  "counter": 5,
                  "key": "tESv9OvCcOVPq+SeQAf6DsfDcJnw0BJ0r9iVLq+YE68="
                },
                "chainType": 2,
                "messageKeys": {
                  "0": "gVvuljdPf2vrlAZD58k4YunhKuNpNxkQoa9qkNikmkQ=",
                  "1": "OJg6QYocPDIPZhFFVs9/+RvZ4RMv5VSfrafzp4ejpYc=",
                  "2": "zYdlwSXLjiZ3Zo7cDgxZ7u7YFRvb5zLkS+hVZr90M7U=",
                  "3": "xwKnIykK6VjfuRIf3HWAMsSXVVfTzBINkCohiRVWa64=",
                  "4": "rjsFfzU8JkfPPVBTm7WxG376Ac3UH3RHH/WlO4+RdGg="
                }
              },
              "BQOeIvGl1UWp2attWeeAW7YG/Qt2j5YN8ywY9WGeWGBp": {
                "chainKey": {
                  "counter": -1,
                  "key": "LaXEuZMz8JOuns0cTKEnjM8eK2WrzEZwt0dkIEz+lRg="
                },
                "chainType": 1,
                "messageKeys": {}
              }
            }
          }
        },
        "version": "v1"
      },
      "6281229951374.0": {
        "_sessions": {
          "BV8a3BpGRVYWY03QJcI1z5Uzb6qhVRe5O7YDuJP2p7ZW": {
            "registrationId": 672127419,
            "currentRatchet": {
              "ephemeralKeyPair": {
                "pubKey": "BXjX77TcdEZ4/HcLmOYLxUi3LeQIJeyamUQ4uYaaZFc5",
                "privKey": "0PisZ4TzucGdvUf2E/a3rUHuU64+QKdUvdA70FLehmU="
              },
              "lastRemoteEphemeralKey": "BZaWvXH901gs6AytP4UZfspUIEG4e/F04zZrf5ZSuwtd",
              "previousCounter": 0,
              "rootKey": "U+pk9vWxnNljYJML9gBJ4xM+fLKyJUrG+eNJ6TPVfYo="
            },
            "indexInfo": {
              "baseKey": "BV8a3BpGRVYWY03QJcI1z5Uzb6qhVRe5O7YDuJP2p7ZW",
              "baseKeyType": 2,
              "closed": -1,
              "used": 1664638893731,
              "created": 1664638893731,
              "remoteIdentityKey": "BSgz3seY2UHs3DPmVXJrfWvwHb80BadyguY/CPSYo05B"
            },
            "_chains": {
              "BZaWvXH901gs6AytP4UZfspUIEG4e/F04zZrf5ZSuwtd": {
                "chainKey": {
                  "counter": 0,
                  "key": "tjOMRpMqZMxEw8EdpyK93aGaOtGvbNsNwA9BOX3pzfY="
                },
                "chainType": 2,
                "messageKeys": {}
              },
              "BXjX77TcdEZ4/HcLmOYLxUi3LeQIJeyamUQ4uYaaZFc5": {
                "chainKey": {
                  "counter": 1,
                  "key": "MjfucrjQXmqX/rSMTiybcQ1+zB6qXLXjHfT1WH+zmwg="
                },
                "chainType": 1,
                "messageKeys": {}
              }
            }
          }
        },
        "version": "v1"
      },
      "6287711515793.0": {
        "_sessions": {
          "BS1iFcIYCl1zXfmUNbgXhUpRgty8IpIpMQfx+fGwA4ga": {
            "registrationId": 1797044071,
            "currentRatchet": {
              "ephemeralKeyPair": {
                "pubKey": "BfPJ/UQRFRgQbJ0NnqcYlYGLJCZRpE3wi0ANKvQ4Tf0p",
                "privKey": "yNliPB3xSmW7cmFBgJ3RE7U9iXbII20kPKPMD9TmSHc="
              },
              "lastRemoteEphemeralKey": "Bd7mAvncfthpcL1NF1HhaR7B1m93hMv++eZRoLVq4J9p",
              "previousCounter": 0,
              "rootKey": "Asot87KEQ3l6ctEDPAkeJZSYBqaIZFzwaGPmDKK3TVg="
            },
            "indexInfo": {
              "baseKey": "BS1iFcIYCl1zXfmUNbgXhUpRgty8IpIpMQfx+fGwA4ga",
              "baseKeyType": 2,
              "closed": -1,
              "used": 1664641692979,
              "created": 1664641692979,
              "remoteIdentityKey": "Ba9x6yVK+3ADp4XxH04vUztgHH3+adDrw6RJ9OhjZ+Y4"
            },
            "_chains": {
              "Bd7mAvncfthpcL1NF1HhaR7B1m93hMv++eZRoLVq4J9p": {
                "chainKey": {
                  "counter": 6,
                  "key": "SSgO/7rlbNSIfg33yRxITBhJ9mO0Fj01rDr98y4pNak="
                },
                "chainType": 2,
                "messageKeys": {
                  "0": "BP1G8m1S5MIwOrAJdEQFyTGE4A90DNEtv/uYj3L2HBE=",
                  "1": "bSINRc9qYQhwmGSMMSBfqxuGRUX5mvE5U/8lhtgwXcE=",
                  "2": "6XTH3A86d2WvNBV+3lRSPI8NGo77uNzDJ3p8fPHdLH8=",
                  "3": "ZEFcWXTwbZKWpHC7rLqO60+2LmaEMHpV/YZNxVrs9Rg=",
                  "4": "F3BNz+oOITFzF39+rRlCgHolFFcmTcdjHE+nQAq83a0=",
                  "5": "wPkZYfVfHrQB48lSo/XKQu7tkwgEZ28FNPZrjvRQMY8="
                }
              },
              "BfPJ/UQRFRgQbJ0NnqcYlYGLJCZRpE3wi0ANKvQ4Tf0p": {
                "chainKey": {
                  "counter": -1,
                  "key": "nPdqkDdnNW6/7oOAw4XOPHnkCBGZD7D9uR0zLsXhiB8="
                },
                "chainType": 1,
                "messageKeys": {}
              }
            }
          }
        },
        "version": "v1"
      },
      "6285229978098.0": {
        "_sessions": {
          "BXKVixHYe6nKZ2Jzv8fekt2E1R2BbQCOL2CKdJD/M9Qx": {
            "registrationId": 146389557,
            "currentRatchet": {
              "ephemeralKeyPair": {
                "pubKey": "BbDdDcBCh3Pg34mX79CsQGVqByL1X/lf23LYhWNSbAZ5",
                "privKey": "WD+fgukiQkwfM9g9CUxoiQOW2kglJW4cb+Eb2NImznY="
              },
              "lastRemoteEphemeralKey": "BUQEBIP6MpaPQG6u9XdN7LWmCbDo+tpUFTwCdoyyUeNr",
              "previousCounter": 0,
              "rootKey": "2t4j/RyyUJUhg74B/6laRKQgL3ntGjCJsKJi68FAC94="
            },
            "indexInfo": {
              "baseKey": "BXKVixHYe6nKZ2Jzv8fekt2E1R2BbQCOL2CKdJD/M9Qx",
              "baseKeyType": 2,
              "closed": -1,
              "used": 1664642578416,
              "created": 1664642578416,
              "remoteIdentityKey": "BVeyFJg/UmwJKfZYLm4T/5jDiiGpkTtBS8fEVijfmqtc"
            },
            "_chains": {
              "BUQEBIP6MpaPQG6u9XdN7LWmCbDo+tpUFTwCdoyyUeNr": {
                "chainKey": {
                  "counter": 0,
                  "key": "WkpBkIxRbx+l+glugDZMcttmIfG0jPDs0p/2BAwzjxI="
                },
                "chainType": 2,
                "messageKeys": {}
              },
              "BbDdDcBCh3Pg34mX79CsQGVqByL1X/lf23LYhWNSbAZ5": {
                "chainKey": {
                  "counter": 0,
                  "key": "WGfLcyO+NNpzIZ6oKVimc46TXXWc6oTGIvMLNxoTWk8="
                },
                "chainType": 1,
                "messageKeys": {}
              }
            }
          }
        },
        "version": "v1"
      },
      "6289653550322:19.0": {
        "_sessions": {
          "BU+lw0tVGO54ONW3HavWuP9XdOuFRMj3ZZOgkc3io1RT": {
            "registrationId": 740,
            "currentRatchet": {
              "ephemeralKeyPair": {
                "pubKey": "Bb+2Qtsddu7JJz2mnKygcmJ5BKgvZwLmGlwze/iHZE9d",
                "privKey": "kEoI7TVhH9AcbUtSfnWD9l+O9o15N24wCfg+YVrZt3w="
              },
              "lastRemoteEphemeralKey": "BbJQ7TkAb08VP2GqmpjIMwU1lJ3keuCnnel2iv7yMPgw",
              "previousCounter": 0,
              "rootKey": "QCw7uClQ+rLnPBApGEc3zcvg319NhoTALJ2YU9fwjVY="
            },
            "indexInfo": {
              "baseKey": "BU+lw0tVGO54ONW3HavWuP9XdOuFRMj3ZZOgkc3io1RT",
              "baseKeyType": 1,
              "closed": -1,
              "used": 1664642589830,
              "created": 1664642589830,
              "remoteIdentityKey": "BTwJvtzKbYVEANMo84FGMS6jK2ACNBpHoEd4uJ42Y+VT"
            },
            "_chains": {
              "Bb+2Qtsddu7JJz2mnKygcmJ5BKgvZwLmGlwze/iHZE9d": {
                "chainKey": {
                  "counter": 0,
                  "key": "wCDjC3BgtObzjVfOXqbwU47Im05aOB1fSDErs2gwmr0="
                },
                "chainType": 1,
                "messageKeys": {}
              }
            },
            "pendingPreKey": {
              "signedKeyId": 2,
              "baseKey": "BU+lw0tVGO54ONW3HavWuP9XdOuFRMj3ZZOgkc3io1RT",
              "preKeyId": 577
            }
          }
        },
        "version": "v1"
      },
      "6289653550322:20.0": {
        "_sessions": {
          "Bah1U0S6SxfjlbKDbO7auwgTiIT56A6ummLQPZafbGkN": {
            "registrationId": 6431,
            "currentRatchet": {
              "ephemeralKeyPair": {
                "pubKey": "BZmW+Cu3tVP5bA2UcKO4r38ZRLi3af5uoqmO9ilIICAC",
                "privKey": "aJ03J6uooEMzD2QsLLeTV7TjmH0/VB7c0pMSkPWcHUQ="
              },
              "lastRemoteEphemeralKey": "BduuqI3YtAGjoz2m0x3fwRPdosJQ2E6W/rR5xPpth5Y9",
              "previousCounter": 0,
              "rootKey": "FSlG4JU4lWzWdaB8OBFDFSXvCrmQyDYTzpknkdNEghw="
            },
            "indexInfo": {
              "baseKey": "Bah1U0S6SxfjlbKDbO7auwgTiIT56A6ummLQPZafbGkN",
              "baseKeyType": 1,
              "closed": -1,
              "used": 1664642589836,
              "created": 1664642589836,
              "remoteIdentityKey": "BSyKot8/yv3/iu6OLNJk37UvnWPEjs8DUnzzjztsdGYJ"
            },
            "_chains": {
              "BZmW+Cu3tVP5bA2UcKO4r38ZRLi3af5uoqmO9ilIICAC": {
                "chainKey": {
                  "counter": 0,
                  "key": "MIruY2rNQcDOQdYjqAO2B5SR/u3Zg4nlbKT1CTp/DHk="
                },
                "chainType": 1,
                "messageKeys": {}
              }
            },
            "pendingPreKey": {
              "signedKeyId": 1,
              "baseKey": "Bah1U0S6SxfjlbKDbO7auwgTiIT56A6ummLQPZafbGkN",
              "preKeyId": 148
            }
          }
        },
        "version": "v1"
      },
      "62853267948341.0": {
        "_sessions": {
          "BaMWj16by2+eQBwXIzKCFuFKLn26RJM0DFvoY9LzQVN+": {
            "registrationId": 892026101,
            "currentRatchet": {
              "ephemeralKeyPair": {
                "pubKey": "BbrrfZl6rR0zUQftS4066YX5wL+FU1CqjfHnRDPwmuZQ",
                "privKey": "6Aze2bJuVnuHdvcI+gom1EdvFIgwm9yt+cwybiHHtEk="
              },
              "lastRemoteEphemeralKey": "BXfXT1YncxckeCkiLAvey2IvutG43ZaOTeXesAD37qdi",
              "previousCounter": 0,
              "rootKey": "pSsvHZ0b/e1L8hBCG9CouSXhmUq/jZLtehny9cIDIQk="
            },
            "indexInfo": {
              "baseKey": "BaMWj16by2+eQBwXIzKCFuFKLn26RJM0DFvoY9LzQVN+",
              "baseKeyType": 1,
              "closed": -1,
              "used": 1664642589840,
              "created": 1664642589840,
              "remoteIdentityKey": "Be7Dj34g2okjSXG1pfCAPvL7JHtFtye6BUEZzHx2SuxV"
            },
            "_chains": {
              "BbrrfZl6rR0zUQftS4066YX5wL+FU1CqjfHnRDPwmuZQ": {
                "chainKey": {
                  "counter": 0,
                  "key": "J4EJEMCxI69bZLIubkD1isu2uuhDp4009i4AAfG0bvE="
                },
                "chainType": 1,
                "messageKeys": {}
              }
            },
            "pendingPreKey": {
              "signedKeyId": 1,
              "baseKey": "BaMWj16by2+eQBwXIzKCFuFKLn26RJM0DFvoY9LzQVN+",
              "preKeyId": 5139322
            }
          }
        },
        "version": "v1"
      },
      "6285329711696.0": {
        "_sessions": {
          "BVeaBvk4LdDLk4lmUpj70urt9Zi6TXwui3PAhAOzl5AB": {
            "registrationId": 83720538,
            "currentRatchet": {
              "ephemeralKeyPair": {
                "pubKey": "Bb+X/e5hiwE+O9+1csetBTuUzSooiOfLXtuMXXG/pJhH",
                "privKey": "ILCZ4fvRtteFMqwdHCLswSfa3Ray+5WKVgW3XVwAykw="
              },
              "lastRemoteEphemeralKey": "BYfsX5YnKnUNJ8pXCtJbvCLUl3fuh3rK7gy69ffNnIwO",
              "previousCounter": 0,
              "rootKey": "qnkoLALmN2JIXOpWJc2J0OARVQm7fzdx+ewHB9Ck4WU="
            },
            "indexInfo": {
              "baseKey": "BVeaBvk4LdDLk4lmUpj70urt9Zi6TXwui3PAhAOzl5AB",
              "baseKeyType": 1,
              "closed": -1,
              "used": 1664642589844,
              "created": 1664642589844,
              "remoteIdentityKey": "BQsJBihhe5mIz4vpkrrau4koEEJiKShPDf9IDaDHGL5h"
            },
            "_chains": {
              "Bb+X/e5hiwE+O9+1csetBTuUzSooiOfLXtuMXXG/pJhH": {
                "chainKey": {
                  "counter": 0,
                  "key": "X3RcJOtPPqnD3Cp9A6x2RM/ajI8hDc73IQcHwzQYM38="
                },
                "chainType": 1,
                "messageKeys": {}
              }
            },
            "pendingPreKey": {
              "signedKeyId": 5,
              "baseKey": "BVeaBvk4LdDLk4lmUpj70urt9Zi6TXwui3PAhAOzl5AB",
              "preKeyId": 14184576
            }
          }
        },
        "version": "v1"
      },
      "62895342161166.0": {
        "_sessions": {
          "Bb46bh+CQlMRULysiCGotC25Zm8rXVECCAX6OV6YI3kq": {
            "registrationId": 1145813420,
            "currentRatchet": {
              "ephemeralKeyPair": {
                "pubKey": "BdB8lHDC5RwJddJouecfqpQgah2am4/iYw0Ot80+/Aol",
                "privKey": "MArtQEHqXjJV4YsSHy5P9bWQBBOVXPktKdiq25Vs7ls="
              },
              "lastRemoteEphemeralKey": "BaRsuh+hOMOtg3z5aDkTo//5dK8xG7GI4Uc5if4NaHos",
              "previousCounter": 0,
              "rootKey": "RHKWdmtfxNH71th7Xx5zOu3ppBBwIJbzw1WpHxBWtX8="
            },
            "indexInfo": {
              "baseKey": "Bb46bh+CQlMRULysiCGotC25Zm8rXVECCAX6OV6YI3kq",
              "baseKeyType": 1,
              "closed": -1,
              "used": 1664642589848,
              "created": 1664642589848,
              "remoteIdentityKey": "BVrH7W8oUkWEdO+sCgUzAso0AFsNQX+7c0Sma/e7MVFH"
            },
            "_chains": {
              "BdB8lHDC5RwJddJouecfqpQgah2am4/iYw0Ot80+/Aol": {
                "chainKey": {
                  "counter": 0,
                  "key": "cgQvAOAso8JyYNkIfu4RRJVTeV6fHLVppsjgKLQcmF8="
                },
                "chainType": 1,
                "messageKeys": {}
              }
            },
            "pendingPreKey": {
              "signedKeyId": 15,
              "baseKey": "Bb46bh+CQlMRULysiCGotC25Zm8rXVECCAX6OV6YI3kq",
              "preKeyId": 5884681
            }
          }
        },
        "version": "v1"
      },
      "62895364635174.0": {
        "_sessions": {
          "BbcNz/6eAkmN12YXSVohim+1Ka9hS1W8EsZfT/TovIon": {
            "registrationId": 742244042,
            "currentRatchet": {
              "ephemeralKeyPair": {
                "pubKey": "BRS4mHwdacxfOZ/ULwwDoTgw7/UJN/i4VmionbL7utoJ",
                "privKey": "UGPeSn3DltA5If31/lbIMkSOXdn1rz+HnaRMNR3VyEY="
              },
              "lastRemoteEphemeralKey": "BYIcGlqehTNbBJn6+8XPLu/y1ls3hFXyTm5rfg23WPkU",
              "previousCounter": 0,
              "rootKey": "rBjPMoV9+4MjPkT/RL37pRGWUSOvymZSKpTOTDMDDpE="
            },
            "indexInfo": {
              "baseKey": "BbcNz/6eAkmN12YXSVohim+1Ka9hS1W8EsZfT/TovIon",
              "baseKeyType": 1,
              "closed": -1,
              "used": 1664642589852,
              "created": 1664642589852,
              "remoteIdentityKey": "BUv/59Mk/Ng2uRuFBWtdFVV4xlBV7yBSlWlTrzbh8ucO"
            },
            "_chains": {
              "BRS4mHwdacxfOZ/ULwwDoTgw7/UJN/i4VmionbL7utoJ": {
                "chainKey": {
                  "counter": 0,
                  "key": "/0XKGsqkRFP7ONc9B3S4RhEnHbfTbl+6k8IgUqtRpX8="
                },
                "chainType": 1,
                "messageKeys": {}
              }
            },
            "pendingPreKey": {
              "signedKeyId": 4,
              "baseKey": "BbcNz/6eAkmN12YXSVohim+1Ka9hS1W8EsZfT/TovIon",
              "preKeyId": 283508
            }
          }
        },
        "version": "v1"
      },
      "6289653550322.0": {
        "_sessions": {
          "BSPz/H+AMTgw8PIyW943/a79s3HsJyue1X5xRSZ+eio7": {
            "registrationId": 482367789,
            "currentRatchet": {
              "ephemeralKeyPair": {
                "pubKey": "BSRTuZM54fO1JduKyckBhXmBb3CsFZzL+5R8YQW4KcJg",
                "privKey": "uFRKHIxAR9M8QkzHJjSbo0he7/p1AOxCeWlTZB5oum8="
              },
              "lastRemoteEphemeralKey": "BYDP5J9dwEEhydjrIdegJ4BnlTb8INIRUq1My5IC4ZJb",
              "previousCounter": 0,
              "rootKey": "9o93n/Ub+zpfz8y3dLIjcGFyUm3V1GWm88oEoTt2Ez8="
            },
            "indexInfo": {
              "baseKey": "BSPz/H+AMTgw8PIyW943/a79s3HsJyue1X5xRSZ+eio7",
              "baseKeyType": 1,
              "closed": -1,
              "used": 1664642589856,
              "created": 1664642589856,
              "remoteIdentityKey": "BbyXyyF9d9ym86HF1V80AtqB3lTzJtpqUsNDZ4C2e49M"
            },
            "_chains": {
              "BSRTuZM54fO1JduKyckBhXmBb3CsFZzL+5R8YQW4KcJg": {
                "chainKey": {
                  "counter": 0,
                  "key": "LH1a+7TmMunBSRs4TVCpmfH3qZKBGaN7dep9KElqs/s="
                },
                "chainType": 1,
                "messageKeys": {}
              }
            },
            "pendingPreKey": {
              "signedKeyId": 1,
              "baseKey": "BSPz/H+AMTgw8PIyW943/a79s3HsJyue1X5xRSZ+eio7",
              "preKeyId": 5536903
            }
          }
        },
        "version": "v1"
      }
    },
    "appStateSyncKeys": {
      "AAAAABsr": {
        "keyData": "CDje29zYr574nRkj7e9dmlA+UG4+GHX2uCDIYPKJiLo=",
        "fingerprint": {
          "rawId": 619537953,
          "currentIndex": 1,
          "deviceIndexes": [
            0,
            1
          ]
        },
        "timestamp": "1664366063044"
      }
    },
    "appStateVersions": {
      "critical_block": {
        "version": 1,
        "hash": {
          "type": "Buffer",
          "data": "bSR6imViYsvIB9NwG7XMasNkouHBJzdRuwunK+Jffbbu6US+tCVkeQLYG03YpYI+L0XC1sfZzTmJq7NSLQl/rz/2+EXx0dcpCPyIplCgrh2cWV1MSXxNy2voPGkG6wnZVFN/BmGfwIhpiRxCvA6AgxeXJcoHPmSwMnO6231H/eg="
        },
        "indexValueMap": {
          "hcfl93M63vb1OFAIeaVn1ASyfL4zvpIG7N4zoGw2ah8=": {
            "valueMac": {
              "type": "Buffer",
              "data": "dHWEQdFuBACJWJRDrpt4tpdUx/tPN1qXZHDNINXnCh8="
            }
          },
          "lnJ0fwq2BSWeyddwYL9WfUF48AwM8lJNbW1q5TKQzrk=": {
            "valueMac": {
              "type": "Buffer",
              "data": "wHk9ES86xhPF7jsONWcrLMJ+PLynCv0tRrDNiAP2KGc="
            }
          }
        }
      },
      "regular": {
        "version": 1,
        "hash": {
          "type": "Buffer",
          "data": "/YGtye23SC1q0gLCy/LKPKSP+1VgdJT5l/epoRWGoVz12/ve9Gx4eElGXSgL+z9LtoncPmGcF1uUCCt1U3J+S1p7g4vW7lqhx/z0/vApmzhFhr5v2A0yQA7icwUgkliLW/wofJJcN+VS6oKHNb1sRgU2Mn7SQAmAl4TFhtyN3ZI="
        },
        "indexValueMap": {
          "msybx4g5QIWIJ45eknEixstJ6kAKgZoOsPdKT0a4qyU=": {
            "valueMac": {
              "type": "Buffer",
              "data": "vbtU/FLfOIiw4ulWeI5CbOnkiP75Hon5bsmuGl51zO8="
            }
          }
        }
      },
      "critical_unblock_low": {
        "version": 1,
        "hash": {
          "type": "Buffer",
          "data": "wNAWVHbt0OvA3g/mHb+QRpjEGKaz62a0CHi+0yBH5iUF+s2wwm/f4PhnvHho1DP1/81ZTFMHuUKA3d4oUZ/xAVNZE6CZIsKoEiSYOJHmk2W9EVa4RsaWTMzvZZTc15uQBH48zHeCDrQXxAa2DUOm093pB4Cr5/1FVkbE/jmZwZ0="
        },
        "indexValueMap": {
          "81hs8IqGuY9JNvr5rMeZYPOnRRU86Hpkk0Z5FsWQF+c=": {
            "valueMac": {
              "type": "Buffer",
              "data": "HZiX9jl8V8DBfjblmZrYpF5G0MT9yX58qlHncprO14Q="
            }
          },
          "Ulii6TerOKavAFyzjtSR0kLK8fBAJlzjV6xTBHyOT6k=": {
            "valueMac": {
              "type": "Buffer",
              "data": "ApzMHQO+XcIi5ipmQBTP3JEag74qP1jClHT75NBhWCA="
            }
          },
          "1i1TNMnUhZ7i0rmM5J2F5So25dFMmaavW1xO2FuiP1g=": {
            "valueMac": {
              "type": "Buffer",
              "data": "Y9DPeZk7m1CbU8aQ9MEnJO5fGLd/2Et2/bdydr/1duM="
            }
          },
          "EyIbIoa5zxBYCzyzkEh14+BW/tLpCG969ECK+j9VUxg=": {
            "valueMac": {
              "type": "Buffer",
              "data": "Hbj4rzqKNHmZ7TwRBoLEk3rrYFWkcb4Gz85KT0y0jPE="
            }
          },
          "VM5JFOK6xpYr5I5io3wCzf21IAqm2x/sdcL90T+ZH7s=": {
            "valueMac": {
              "type": "Buffer",
              "data": "Vj4L8ng87CXn0FzT3DQqoZjrTiRyfVOe4lIr3n56hnk="
            }
          },
          "RLJyv379/i5r6r8nP4dL5LxBVoZGWtxOXr0zrmZ93yo=": {
            "valueMac": {
              "type": "Buffer",
              "data": "J7Frmy+DWR5D5JWEV7g8+fj9yiVKqoxy4L2a4F9qtZ8="
            }
          },
          "JXDlPL4lAmfpmMelXXxGhSnEgEWor2lA8bAXdWOmZao=": {
            "valueMac": {
              "type": "Buffer",
              "data": "SCDcNOlKE4B+BVCf5DaqZEqnHa82mYCjlowuiyG+xqE="
            }
          },
          "V1KKXfy1q1GbgkzFG8n+E6Ufh5CjgJGEu4cZ1T4DTsc=": {
            "valueMac": {
              "type": "Buffer",
              "data": "9vi5D3DF5v0imCnG3orql8RT6Gnu2Wym07XZZCTJi0Q="
            }
          },
          "j/a4N46psIq1Orn6dywDqOhtAqrd3yo/mHZVobLyu8w=": {
            "valueMac": {
              "type": "Buffer",
              "data": "MSBSvhuWYRG0yCC04KlawhvIeRq7iGV7iI3djhTX0G4="
            }
          },
          "WMjfvwqkzHX+uQsdsPQBlR5Zi5evnU+9ue8x06yKcFo=": {
            "valueMac": {
              "type": "Buffer",
              "data": "Kax0NiBd329r6lBZCSEGj3gTjRsaqPdk3aY3Vc0hChI="
            }
          },
          "WZ7lZQN/fhg87KWoalnutnZ/GpMD27jJrKvfS7u84BQ=": {
            "valueMac": {
              "type": "Buffer",
              "data": "5vyh/PZQDlXbVOpAOVhBlkJsBZ2dAcA7YCF+L9JUak4="
            }
          },
          "21K+Q5RuzVMBanrpvwnR9lyCj1Zc9RKKn2TCVHN1bYQ=": {
            "valueMac": {
              "type": "Buffer",
              "data": "dYpnV35UBjs8QzmMEPDI3Pi6NuiHbFJXR7+hkKJR1IA="
            }
          },
          "YfPaSYuFJr9L4YoDVYhPQZPBA+WDl2Yld50a2jLxWyc=": {
            "valueMac": {
              "type": "Buffer",
              "data": "tXgM/+fMveERQNHLhteIHvQU0JmZxcD5R+vwh0s1IBA="
            }
          },
          "DroAxxpX7OtdN/N/4VhLG7T+8Jj5UqpHQ1RP/0P9LJA=": {
            "valueMac": {
              "type": "Buffer",
              "data": "XxAGS0PtCXrmkfB0lCGv1yyuEoTxlupnoEaW2q36LSU="
            }
          },
          "2s2rSpH0pSnoDGiE5vzgEpb4+423VZEQg07dKVu0kZQ=": {
            "valueMac": {
              "type": "Buffer",
              "data": "sQTOLkaBZ+wfupilbz5G3QxAYk1u6rDOLsaSv0OUBW8="
            }
          },
          "e8xukRCTlnpI3oW1SORwbsRyAT6Z5DyhtFZkv78U5ek=": {
            "valueMac": {
              "type": "Buffer",
              "data": "uUf1YlXTroy0KxOkAwcBKa35JVaJEzMQt1btYiM6Zes="
            }
          },
          "HcjtT7RpML7xfFjLSh3UupsOi7FCbf2pZ7O3gbtdUlQ=": {
            "valueMac": {
              "type": "Buffer",
              "data": "kIPbTcpaFZ0aZjzwNe1ij1Z3pW1ea4oMfXRX6VJAIac="
            }
          },
          "mzxOZXUKMZ/adAtrwawLp7mCp7oTWov+Vocp65+EgL0=": {
            "valueMac": {
              "type": "Buffer",
              "data": "cnhUfNQAFLvK3dileTNa1IgcczBbMcsylXPCvehIOKM="
            }
          },
          "E+RhNlKz5dtShAC9LXM+R3TCrmSpimza0w1e6K6E6Yw=": {
            "valueMac": {
              "type": "Buffer",
              "data": "7jMOnT4NG5ZqOd79aT3uTZLJPXAhrB0SWlj6Nbeidrk="
            }
          },
          "w1lTXkAOo+aT+Nif9f4uvtU2iJ2IyGGE4yHHvU1sFQI=": {
            "valueMac": {
              "type": "Buffer",
              "data": "Y+T5C048MjcXAmz1kQhwfARwUL1lLqTOLRNdLwRoQZ0="
            }
          },
          "sAduzFL0HT2biw2CSm8/E62wBIiEUbf/y9Zy9mGmNCo=": {
            "valueMac": {
              "type": "Buffer",
              "data": "GfM1n5as3qxH+H0FfEIk99QdagZRoWXPxbYlytD0hQI="
            }
          },
          "YSVH3yLWNrdooFa09IoYRfZ8bxxxlZFcbzuZx4vsjlU=": {
            "valueMac": {
              "type": "Buffer",
              "data": "RSeejC1zsdu5GZs7OO8Z6VEoa/HonBkOVMFzqIwgTF8="
            }
          },
          "D4Ov6iWXKSqNhHKtSGMF8on8TEhSMpXq4tyMvLhGcCM=": {
            "valueMac": {
              "type": "Buffer",
              "data": "lHelXNoos+i3JlRTPdVevz8lwoDSvTwW6+tECJHcbX8="
            }
          },
          "mhYdQnv2hHZip8UB0PxoqbFtz1PkKFJUBNTVFxQibHg=": {
            "valueMac": {
              "type": "Buffer",
              "data": "PR6A5KTf0MB6ZP3EtA9NUXTPdfgvFhyyzQvyT19uxhI="
            }
          },
          "vWDC0iOcshcpxyKJ82sAfOODozTBUjkCkVVdq0XBfkQ=": {
            "valueMac": {
              "type": "Buffer",
              "data": "fh4foulnyjhDtYNfgj3oiKfdXmclzWbVk2k8AAGjdpc="
            }
          },
          "kCYMKWTFtrsf5IcXY6ku+l8lUFy2KBoeYpyE1gNMKSc=": {
            "valueMac": {
              "type": "Buffer",
              "data": "ZzAhk4b45fTM0zBQII3d6T4a3Wp84aR0IN8TlY8szgU="
            }
          },
          "8MvgTsU5aNEcLKq5hdD00LN3j2X7MKh1ufKuVC2EdxY=": {
            "valueMac": {
              "type": "Buffer",
              "data": "FI7ArKARLxty2nmrM2oyTYc6YTD4sRafd/BYnw33gAU="
            }
          },
          "T0JvZYMA5m4/Hia5WRPJXDuoRb4JfQUH2OSP5Bm7olo=": {
            "valueMac": {
              "type": "Buffer",
              "data": "hgJySchTCGGuqit0clS7TfiQVD25zG+y1EFEI+pGDYc="
            }
          },
          "kCyfjv54RV1SDWol2xLgtBJ3TAB5r7ujU0tbE6Flsj8=": {
            "valueMac": {
              "type": "Buffer",
              "data": "ZF0b6TpHx3926bHMLVgaPoORTKOynUDh7MX32WJt0DQ="
            }
          },
          "zGzIFZWjqSXtOKsITCOeqASzdqfAG+qMi4my7nSrvS4=": {
            "valueMac": {
              "type": "Buffer",
              "data": "EaLVB8uuK0C3KlCLzHlnRNXvrWDPo6PZbUepxGk9m6o="
            }
          },
          "/86mz7ASLSygcBrwFirvWdPuaffKo0qw105xtr67jlA=": {
            "valueMac": {
              "type": "Buffer",
              "data": "vc8hJXJU/nFpVvrmkZuzTaAOerR9SSonqQ9zSRgUWpg="
            }
          },
          "ixIqIQqYscoEuMIhgPOzwVS0aqJLNF2Dx1+7onbm52U=": {
            "valueMac": {
              "type": "Buffer",
              "data": "nzLkfcbwicHBJWSj35TSqCwpamDcG4XTXYUl3TzUC5A="
            }
          },
          "CHlarsGtCoPSAKjl6meiXdfZICdKfzXGd/vaZRaVrS4=": {
            "valueMac": {
              "type": "Buffer",
              "data": "vgcuQJVQNOEa8wD62wWkbtJPG417Ra6ERe3Ekm9Dzc0="
            }
          },
          "7mHOK28EjeZ1VQfcJADOumAFpWBXqcdNWUPviRAUrIA=": {
            "valueMac": {
              "type": "Buffer",
              "data": "sjonL3oYN4zqNS2mT9PaC4t91oiXoXVguaD/DOwNINw="
            }
          },
          "GwpgV/pQtSSMLb/zeSzAHf6V+JFH/TXpTm8ARITVgeM=": {
            "valueMac": {
              "type": "Buffer",
              "data": "b2DyI36KTGgcfdifK4+4Qxu/ovWX1jE/PI9LW79q+2g="
            }
          },
          "LDdyOpm0cN/7CfiWPTX0Gg3N3xQDX7ry8YpJj/OBWhY=": {
            "valueMac": {
              "type": "Buffer",
              "data": "lsfTPeUYeOL+N3LUqLRo5SFEbIkmL/oCF8jndbDysCo="
            }
          },
          "nQqcP1Xxuw4GaYfyisv8In92SWLBPf+NV81nsDtmF30=": {
            "valueMac": {
              "type": "Buffer",
              "data": "dsCjfbS+PYYh8S/rp6TmDhbV9l+rasKdhiYuAE6PW9Y="
            }
          },
          "1Tp25bgOoeBuN3fQ1fCrbiMksNxgM+PUqMJE7/orjI8=": {
            "valueMac": {
              "type": "Buffer",
              "data": "pcuwoJxhDy3YsUbgQr74PyGI9xCOApLQRDUGnpOsxqA="
            }
          },
          "VZfrRfELJfTHCm/u1QhUrJxMWw8dC/1q6ll6HnU0xYs=": {
            "valueMac": {
              "type": "Buffer",
              "data": "iV+rfA6fEy45tTfzn29V/Lt3pk/pI0WoeV0ufNMi4ik="
            }
          },
          "fUkp7I9RB4Dq2lWcWf9NSmf/wNtptGLfW5v4Aqf5DcY=": {
            "valueMac": {
              "type": "Buffer",
              "data": "x+ZS/SAJmNOnU9PBecZ/uQBYNlpBmC5lf+yi9t6YzUk="
            }
          },
          "nGQKSSR0UyHuc/kxvZphyIpO88yeQYnebQTXxYfphSs=": {
            "valueMac": {
              "type": "Buffer",
              "data": "qGDNHZ/BSjuw46umYQfSkUuBR++viGcGywBWzLF/ov0="
            }
          },
          "EUNMpMHlZIgjOfweycVN4eH6arXYaStfORxpEBzGt1U=": {
            "valueMac": {
              "type": "Buffer",
              "data": "mlDXPOnPzB3Udk7KLosrDQqWPFESiDlp2SB+2uMIVfY="
            }
          },
          "0UAstGeXEUtxjsCTSIoZhTOf5NnMIzN/n0zosaBCOeY=": {
            "valueMac": {
              "type": "Buffer",
              "data": "cLE+KUqKdzReJuKUtrtRLdBDNzcKxVAI3JXc6xiGYfc="
            }
          },
          "4ITqf2W8EMoAS4fnZfCujc2U40SaRmSBgLym1hWdca4=": {
            "valueMac": {
              "type": "Buffer",
              "data": "g0rrUY7/3Hx92GvLJto+qRJPHbOfg8gEuuHuzBdVNsM="
            }
          },
          "DXFqUDb6gAaW2e2imWx8iPFaNflHMIkyaDDiRY7IjAk=": {
            "valueMac": {
              "type": "Buffer",
              "data": "+l11CINGStPYBX7gWHJqdVVqwje2w6cn0CrxBAUb26Q="
            }
          },
          "ji6UEy3ErK5WafY8rYNUxNmGnnUp8bhzVWEztNNmdTA=": {
            "valueMac": {
              "type": "Buffer",
              "data": "86GIxawibpT+jQPq0Y9FFYSdu/mwklFTE6MEKreIiGY="
            }
          },
          "9vOSVk7+HMe02GaVoAuuiRzI9NdeDB3XVumNAhfcrhQ=": {
            "valueMac": {
              "type": "Buffer",
              "data": "fSKH1s0R5JjArYWTgPR3jFFbe0Ym2+lYEhkWiD+GwgQ="
            }
          },
          "9tGi8qEPyAuW2OGyyVjQoLc0j0itu9g08nI6Owl9pEI=": {
            "valueMac": {
              "type": "Buffer",
              "data": "ARPqF3qKKYOXF8Q3wJ8Gb4phEb3k/K0pai11vollOkM="
            }
          },
          "uHF93yr8yokvq5UL2kd8FzuS7xXXnAlSQcMcJE1otVs=": {
            "valueMac": {
              "type": "Buffer",
              "data": "8kJ4TDinb4XspIcTYS0w0DRnoaLW4/QEUUxENtTZwV8="
            }
          },
          "HDVyulRGE939XGkkxL7YgEou4Qu+tTyKJ/USmj8yQz0=": {
            "valueMac": {
              "type": "Buffer",
              "data": "dkTyggjaVz/lXUbKfCgW3kKKRnryUlfo7fwt7h5kN6s="
            }
          },
          "mQU4/I1HbhgS+Yc0oD6f6BCVIljCRkLdvWkJYpvzeKA=": {
            "valueMac": {
              "type": "Buffer",
              "data": "gwDGQ6RCmsKbCCb0rUPWZMsv8BqwcoM7/dkRpUFIQAw="
            }
          },
          "3lkHQ7JEzb5aOa1Cf4PT2DZichtWAWBttNytASBcas0=": {
            "valueMac": {
              "type": "Buffer",
              "data": "asIa9kRKjKOTkUgM/3K8p7AW9ND2g+kmVOzvbCmcV3g="
            }
          },
          "gyAOd419fRbscfGhQgwAkl7xa3lhNqSni9ZvLwQiS0I=": {
            "valueMac": {
              "type": "Buffer",
              "data": "5hDCkbNxaH1VyHupd6yFRcY1y/FFakU7ksalmchnplE="
            }
          },
          "lkF0bEHMXS7UiLiCA69MES58SUubnu26FuwL7BPwCxI=": {
            "valueMac": {
              "type": "Buffer",
              "data": "6emgAHqIRT9wplueNoJDeU4tFtm8kuOSVmXgSqlAKzs="
            }
          },
          "Bfyby+GH85TpMAiDCRnswiK3dxi3RI60RUYAZ1/1ktA=": {
            "valueMac": {
              "type": "Buffer",
              "data": "q5eYdRu98ZdYFMUzkBMpXkfoZ5MqhSiCpZasLN1MEoA="
            }
          },
          "4GkXfuZzPGeNIplOmen9XGt8lSsfVmVMEJ9KZFOFR2M=": {
            "valueMac": {
              "type": "Buffer",
              "data": "VkNitqXuYU4ryD9Z/OtMia7b+WYU9Cstl+XxlYcqQb4="
            }
          },
          "Ipqpr6NoG90tXQdcwn7BIpbSvuE8nvROoC7c+aOZPSs=": {
            "valueMac": {
              "type": "Buffer",
              "data": "0lKbwK/kXVW9AMVXJkuYMHabUw6H4Fig5GG1EGKn+5U="
            }
          },
          "qD/NZM2Xp7e8bjvV8qjpJwXxh/57Rs8roqEhEtexZl4=": {
            "valueMac": {
              "type": "Buffer",
              "data": "LJ6/pCKB1wqbv5LfHlpQvD/dDYqhV6riFbNquco6140="
            }
          },
          "Yz1wYkcfSzfWu5GWGz7+UIDB/FuBnHDzr6nvuguFtrY=": {
            "valueMac": {
              "type": "Buffer",
              "data": "8C/U3soN7/meiZb9lOL/Qhs5lyhZSQtNZyavVryznFw="
            }
          },
          "P7q4PiI4WDbejUTROICEactPGTlT+J5grkB7QnXrlwU=": {
            "valueMac": {
              "type": "Buffer",
              "data": "21ddyXrkr1SbngCW3vMpu/6MD+H9tkgClmOxSo1Dw4o="
            }
          },
          "wOD3j5A7ee4NHxk1EWVN+Cpu3eJuCuMbBr4sZpjVYAc=": {
            "valueMac": {
              "type": "Buffer",
              "data": "0bQGN+Rxa8E4ZALMuM++bCqPhEMSMzvLf2NyZpLpwyM="
            }
          },
          "gNWlptwXt4TeoTFrxRBVVDY9QcE9wIm26Dln1BYOLbc=": {
            "valueMac": {
              "type": "Buffer",
              "data": "9aQW58brZmsk6WYXD5/+wMZY1Wb8YRyLBqsyxEYJ7sk="
            }
          },
          "GspyVmQ88FEI38YZSgxS5TLXqn/fyB9kYo/hCJ3BfAI=": {
            "valueMac": {
              "type": "Buffer",
              "data": "b5ZCfvNNp1ksn2+8DFA/ZP3k0ORxYU8FU5IIwJRpM4k="
            }
          },
          "Pp63j48/jiax/nI5nKn0TAriT1ORhNTB4M86TooKSzg=": {
            "valueMac": {
              "type": "Buffer",
              "data": "6Kt87NC1BXHfLi+sjzOMUtzfUs8ctXFV0w+BW1ndIUY="
            }
          },
          "DHF8JQY0nL8hIs4KQhINM/X9OUpgtRYpJAlHZESsXHw=": {
            "valueMac": {
              "type": "Buffer",
              "data": "K/EMr314k/vzMPCHWF6g4PPlRCidmJDeaarU5jNmdyk="
            }
          },
          "SEWh0FoCRVLdwtCi2gRAO8XGU7Nf4Pa1l0W2XAkwYQ0=": {
            "valueMac": {
              "type": "Buffer",
              "data": "v4v1zQdh2xPVU3HDn4ZyHj+IxnuRjrhqprii2Knnz2M="
            }
          },
          "IwnAX5PN/KQug5INyzKwF1NbCT2a+LKCCD1iOhDsWKg=": {
            "valueMac": {
              "type": "Buffer",
              "data": "jcyIxelba8QXBcPsFvWY0otDqYduI95EGGXhrOjhR7w="
            }
          },
          "4kmWGgS8JzjMN6BJ2hXLyMPDUmRwUYulPg+e1SiYpjA=": {
            "valueMac": {
              "type": "Buffer",
              "data": "eetI3dIm9OjDCgqT1wPhl5TL70tZH2OZ0FVeIQTtSi8="
            }
          },
          "YzG4W61HrxaiJbZwFJrIcYCn5Un6Xq4eLjsR0N8I6PM=": {
            "valueMac": {
              "type": "Buffer",
              "data": "YDaxoPVBJnkM2mRkbM2QcwUCD359Y5NPWpDXLxYNwNY="
            }
          },
          "ZJsi6KtV6UuL3iXUS0IKXq5YSd8grCCR+VAlKFTZ+E4=": {
            "valueMac": {
              "type": "Buffer",
              "data": "K1Feu6Xoc0eFCDJdF2NW7RSKJ31Yd9N09RkCW+Rz4kQ="
            }
          },
          "3ZOhfInUnN2VHIQMe+cQXGkuPMMNqRC+1UzX5yKrN80=": {
            "valueMac": {
              "type": "Buffer",
              "data": "fcOFDoojBQG1XGz5WICZzLofd9IrHa1/hGNr7LunXWQ="
            }
          },
          "rpl+N3KB7XXaziaSs9DQ7bBgD1U6TQvZfHBcyxVIDhU=": {
            "valueMac": {
              "type": "Buffer",
              "data": "suGUs2Vsv1/GyWnDx4S/V91XKuuTvs6apNS1gHPpnLE="
            }
          },
          "3dNfNZjdc/WuuzG+kYTbbkqXEAsPxZxlrA9EREUOzVw=": {
            "valueMac": {
              "type": "Buffer",
              "data": "38Gl8hCMgRpaKH4/Fy4jiMI71t225/VNlCAQYSi/cGc="
            }
          },
          "YOIDeNDYncAgHnm1sKvojJR0GvijHZ3ZYqrK5ImNlps=": {
            "valueMac": {
              "type": "Buffer",
              "data": "C/Vm2ZKLgssNi6HoVbF1gPiIoURoPB1mA3of+4G3+ic="
            }
          },
          "/aE4fOLbjzRuE3P0P0y1VqesnEY3xek7nZ80s56x+Vo=": {
            "valueMac": {
              "type": "Buffer",
              "data": "qgBw9MuAdvOE0wNKyXn/vRdGgYO7WVUmqXYfI8ou77w="
            }
          },
          "5szxmywKLtCzQtvCD9M52YhQEKFgjy80Rdf16HURkGI=": {
            "valueMac": {
              "type": "Buffer",
              "data": "KuuHBIiu9WcaVqjRgQTarfD+DPvN+7s5ajv+vp4Ug54="
            }
          },
          "VlQBk4NGrxlh35b9Zq0I451sVn0jPn8njiMfgZAdMJc=": {
            "valueMac": {
              "type": "Buffer",
              "data": "9wtkeqXLaUl355BcP+JDRPv4h4GIHEpDFfHueWs8TdA="
            }
          },
          "UEmS3RGd49TVmEVs9J4882ZvtQ0y+x2oMfiU8hODoFw=": {
            "valueMac": {
              "type": "Buffer",
              "data": "J/kYDiucplUXlI2jXyJlWsuB6fTSu+ldY74no5yzYh8="
            }
          },
          "sa5gLlpxKlS1t7AQQv4No8NHCVvjlsa6RugaTBGZMWc=": {
            "valueMac": {
              "type": "Buffer",
              "data": "KD9BLtDSPJDAPdZ9qpw9IEfpwDifz+oZKLJA8kqV2Hg="
            }
          },
          "l1tZWo6y3wAzI/NPjsUYvxZAlUIoAHXAsmFYgEuX2bo=": {
            "valueMac": {
              "type": "Buffer",
              "data": "k375e02K4yBNrXJ3d5kwNwMOtLi/winOdgRnaLkWOaw="
            }
          },
          "kerMYfOJ4IwnhyHqySdL0E+x/7Jm45qonyMzaIiLSl8=": {
            "valueMac": {
              "type": "Buffer",
              "data": "Cu5trK6JOMXQlrx3WebVZcS16m2rZF+Mq6kVke6gVvI="
            }
          },
          "2R/GBhK9nsSTUFWfTffp9iA+IrvJQ7YSnlbQw8B0Y1k=": {
            "valueMac": {
              "type": "Buffer",
              "data": "RU2EJUQsbim3PVCeJibu9P2RvBKY2qWpCrbbblDo4qU="
            }
          },
          "TCbbDgwe4RWJGJe2KInChlihx/4Xmjaazxzmwxti2BU=": {
            "valueMac": {
              "type": "Buffer",
              "data": "u9H/Il2dNce5+Q2Ki70ZKmNvP3Xk3MZ9Kkyna1v3VVY="
            }
          },
          "DFxHgR4FD3hBqPpdyV7XFB4N7iCLPBcySN66csYpEQ0=": {
            "valueMac": {
              "type": "Buffer",
              "data": "2oi4fwRot/6fJZPkhF737f63kr6lZaQ0bY+9lmYHGAs="
            }
          },
          "LFW9fSIsrAL9SeNvOOAjiXCHs4SkOFIFSjleh0JqRCI=": {
            "valueMac": {
              "type": "Buffer",
              "data": "jT9uvS4AnyxCHsZStq04jUQfrGSzVI4cv5327jXt19s="
            }
          },
          "6VO3/pAyyxGGLyNwS4bZIw/VhLlMwJ4oeCmtYwPXoD0=": {
            "valueMac": {
              "type": "Buffer",
              "data": "eV8/CtgHaWdIX00gMpIu4tq1DgZtdp2JtNiqqzRwxTw="
            }
          },
          "GNZBZJEpfjohidy465xlKqdOlukbIYJzFW5tshLXsGM=": {
            "valueMac": {
              "type": "Buffer",
              "data": "MNFd0BkuM0X0IACsZZBhX4FWw54d8nT3Uqn60ObQeFo="
            }
          },
          "MGv57hxH6/O3HwGluOh6HcgzeGbXVdvspDvXPuGzp4w=": {
            "valueMac": {
              "type": "Buffer",
              "data": "EZ+ADkaDS/OkmzNfB+kIfc3CI6C2FwWsCclhfvvurso="
            }
          }
        }
      },
      "regular_low": {
        "version": 1,
        "hash": {
          "type": "Buffer",
          "data": "YKfZvG606e8OJnbdTILMGmd5NsYzdh6w9pp/48sqHmprhdHEuBAuvVUSRipowXQMUMD/2nOezVI0N431dHaPLQ58rehtrfjxK++5TU8erZ8oIUz6arSILfNBYjHU0gQLHeCNawykiyEpiFQxggX4Vaypg7+DswbmIPL+EiKpCTc="
        },
        "indexValueMap": {
          "H9rNBHGkxUSv3EoqUdOvBKjhdIWCDc8iz1nMKOuNvcI=": {
            "valueMac": {
              "type": "Buffer",
              "data": "ftN4/Je1RHoiGtLl+2EVmBiB5s90aFyby8MThhm9RqM="
            }
          },
          "HIdY6w3W/ZVJpflmMYlFjOy/z/JqizNoKcBUot2Vu6g=": {
            "valueMac": {
              "type": "Buffer",
              "data": "lIxNS8FarvYOv3lYYtsSuJQSAy5GaSHeMdBcslQCJEI="
            }
          },
          "IF3C/1p9/oLIl05CTzmhJPwRnnrpEJRVpJPdQh5p9bE=": {
            "valueMac": {
              "type": "Buffer",
              "data": "IfWx6vXtlVf0fd9r35lPaymR6FxbxaAikmqqqkCN4f0="
            }
          },
          "IuRMPyevptUKTUXSLkdnPin/uxrq+7Xv0p1M1WnTPdU=": {
            "valueMac": {
              "type": "Buffer",
              "data": "VvynCZ0th0k9u2zJmp2Iy2uYbCIM+jqHBcLSLQophSA="
            }
          },
          "ZKRm9McbecXRlsqxxICIFQlt+83QcE0yGfgLu2HAvzI=": {
            "valueMac": {
              "type": "Buffer",
              "data": "86SYMTzbSV07gx3iCnqyO7c6DNzGMtSjShRWoODe2zg="
            }
          }
        }
      }
    },
    "senderKeys": {
      "status@broadcast::6285225665895::0": [
        {
          "senderKeyId": 1571380325,
          "senderChainKey": {
            "iteration": 27,
            "seed": "gIG95cw4g0TIHB/Pm3OLhiseD2OhM37uzb8B9EQgDn0="
          },
          "senderSigningKey": {
            "public": "BZAYxKo4t1P3FiD5FgA0CkcKIiaGAxaqDzD+1VxhbqkY"
          }
        },
        {
          "senderKeyId": 1571380325,
          "senderChainKey": {
            "iteration": 28,
            "seed": "itv8BLwIri2S126cvxGozndYjswl8DuIGjO6P8tznQw="
          },
          "senderSigningKey": {
            "public": "BZAYxKo4t1P3FiD5FgA0CkcKIiaGAxaqDzD+1VxhbqkY"
          }
        }
      ],
      "status@broadcast::6285226643655::0": [
        {
          "senderKeyId": 1371412902,
          "senderChainKey": {
            "iteration": 10,
            "seed": "esJaVAv6qtwtXxe7ZGoxjnhGmg3fzcJ6CiapzgN1bko="
          },
          "senderSigningKey": {
            "public": "BWIirfCQBT3uNAo6iGLXm0RKSwpt72LXLXSz9ZjO6Z1O"
          }
        }
      ],
      "status@broadcast::6281325004641::0": [
        {
          "senderKeyId": 1857723831,
          "senderChainKey": {
            "iteration": 8,
            "seed": "EpzXQ26S7emlfeM5vYs9XwDr7NcEnvDkkliLIvcyiHU="
          },
          "senderSigningKey": {
            "public": "BZTcVauvE59OjlJ5Rf2nFz+sQVIGI21Cb6EEZe+d3G1S"
          }
        }
      ],
      "status@broadcast::6287711515793::0": [
        {
          "senderKeyId": 1080612254,
          "senderChainKey": {
            "iteration": 7,
            "seed": "oDNRDIMy+J0Y1bfTMx8NEkSDzl+Jbh7+lVXPOH1mM+Y="
          },
          "senderSigningKey": {
            "public": "Ba2hfXUvju0Pc6V8I5IdHiQ4qysK+hdoUvBPWpZs7axk"
          }
        }
      ],
      "120363042013232403@g.us::6285229978098::0": [
        {
          "senderKeyId": 2064545964,
          "senderChainKey": {
            "iteration": 70,
            "seed": "LotAGdbrHW8R4c1f07kPJebX0put19YT0aZ+soQ7kBY="
          },
          "senderSigningKey": {
            "public": "BRajyNRG8SFFaVZXfTeW3MRb5E+7a2L3TDlJNMhudOcc"
          }
        }
      ],
      "120363042013232403@g.us::6281325610495:9::0": [
        {
          "senderKeyId": 1958281100,
          "senderChainKey": {
            "iteration": 1,
            "seed": "5slkHBgYLRp72+ZRBiwY+Onat/ISBfAAAF+6Qo3nasw="
          },
          "senderSigningKey": {
            "public": "BWDNOKG3flrESa0OlrOpRUdY0OBuS3U99Q64ILt/Bt9m",
            "private": "uIdqSpAcsWcZD2H1vMgiFKw0HYGH3g8/ve7LkpjM81c="
          }
        }
      ]
    },
    "senderKeyMemory": {
      "120363042013232403@g.us": {
        "6289653550322@s.whatsapp.net": true,
        "6289653550322:19@s.whatsapp.net": true,
        "6289653550322:20@s.whatsapp.net": true,
        "62895364635174@s.whatsapp.net": true,
        "62895342161166@s.whatsapp.net": true,
        "6285329711696@s.whatsapp.net": true,
        "62853267948341@s.whatsapp.net": true,
        "6285326794834@s.whatsapp.net": true,
        "6285229978098@s.whatsapp.net": true,
        "6281325610495@s.whatsapp.net": true,
        "6281229951374@s.whatsapp.net": true
      }
    }
  }
}